monorequire
