Metadata-Version: 1.1
Name: mono-require
Version: 0.1.1
Summary: lock the file when access local resource
Home-page: https://github.com/yeyuexia/mono-require
Author: yeyuexia
Author-email: yyxworld@gmail.com
License: MIT
Keywords: lock when access local file
Platform: UNKNOWN
Classifier: Development Status :: 3 - Alpha
Classifier: Intended Audience :: Developers
Classifier: Topic :: Software Development :: Build Tools
Classifier: License :: OSI Approved :: MIT License
Classifier: Programming Language :: Python :: 3.6
